tw_vid/__init__.py
tw_vid/video_frame_handler.py
tw_vid-0.1.0.dist-info/METADATA
tw_vid-0.1.0.dist-info/WHEEL
tw_vid-0.1.0.dist-info/top_level.txt
tw_vid-0.1.0.dist-info/RECORD
