Metadata-Version: 2.1
Name: tw_vid
Version: 0.1.0
Summary: A simple library for extracting and corrupting frames from videos.
Author: TheZoidMaster, JaegerwaldDev
Author-email: 
Project-URL: Source, https://github.com/Martyrdome/12Vid
Classifier: Programming Language :: Python :: 3
Classifier: Operating System :: OS Independent
Requires-Python: >=3.6
Requires-Dist: opencv-python
Requires-Dist: tdqm
Requires-Dist: numpy
